{
  "reqCompanyAnnouncement": [
    {
      "id": 29950,
      "createdDate": 1771423177000,
      "dateOfAnnouncement": "18 Feb 2026",
      "announcementId": 35803,
      "announcementCategory": "RESIGNATION OF DIRECTORS",
      "company": "AITKEN SPENCE HOTEL HOLDINGS PLC",
      "type": "new",
      "symbol": null,
      "recordDate": null,
      "allotment": null,
      "xr": null,
      "xc": null,
      "xd": null,
      "tradingCommencement": null,
      "tradingSuspended": null,
      "paymentDate": null,
      "agmDate": null,
      "dateOfAgmInitial": null,
      "logoUrl": null,
      "remarks": null
    },
    {
      "id": 29835,
      "createdDate": 1770637158000,
      "dateOfAnnouncement": "09 Feb 2026",
      "announcementId": 35651,
      "announcementCategory": "RATING REVIEW",
      "company": "AITKEN SPENCE HOTEL HOLDINGS PLC",
      "type": "new",
      "symbol": null,
      "recordDate": null,
      "allotment": null,
      "xr": null,
      "xc": null,
      "xd": null,
      "tradingCommencement": null,
      "tradingSuspended": null,
      "paymentDate": null,
      "agmDate": null,
      "dateOfAgmInitial": null,
      "logoUrl": null,
      "remarks": null
    },
    {
      "id": 29768,
      "createdDate": 1770033515000,
      "dateOfAnnouncement": "02 Feb 2026",
      "announcementId": 35575,
      "announcementCategory": "DEMISE OF A DIRECTOR",
      "company": "AITKEN SPENCE HOTEL HOLDINGS PLC",
      "type": "new",
      "symbol": null,
      "recordDate": null,
      "allotment": null,
      "xr": null,
      "xc": null,
      "xd": null,
      "tradingCommencement": null,
      "tradingSuspended": null,
      "paymentDate": null,
      "agmDate": null,
      "dateOfAgmInitial": null,
      "logoUrl": null,
      "remarks": null
    },
    {
      "id": 29517,
      "createdDate": 1768301923000,
      "dateOfAnnouncement": "13 Jan 2026",
      "announcementId": 35251,
      "announcementCategory": "DEBENTURE ISSUE",
      "company": "AITKEN SPENCE HOTEL HOLDINGS PLC",
      "type": "new",
      "symbol": null,
      "recordDate": null,
      "allotment": null,
      "xr": null,
      "xc": null,
      "xd": null,
      "tradingCommencement": null,
      "tradingSuspended": null,
      "paymentDate": null,
      "agmDate": null,
      "dateOfAgmInitial": null,
      "logoUrl": null,
      "remarks": null
    },
    {
      "id": 29162,
      "createdDate": 1765540158000,
      "dateOfAnnouncement": "12 Dec 2025",
      "announcementId": 34826,
      "announcementCategory": "DEMISE OF A DIRECTOR",
      "company": "AITKEN SPENCE HOTEL HOLDINGS PLC",
      "type": "new",
      "symbol": null,
      "recordDate": null,
      "allotment": null,
      "xr": null,
      "xc": null,
      "xd": null,
      "tradingCommencement": null,
      "tradingSuspended": null,
      "paymentDate": null,
      "agmDate": null,
      "dateOfAgmInitial": null,
      "logoUrl": null,
      "remarks": null
    },
    {
      "id": 29158,
      "createdDate": 1765539265000,
      "dateOfAnnouncement": "12 Dec 2025",
      "announcementId": 34827,
      "announcementCategory": "CORPORATE DISCLOSURE",
      "company": "AITKEN SPENCE HOTEL HOLDINGS PLC",
      "type": "new",
      "symbol": null,
      "recordDate": null,
      "allotment": null,
      "xr": null,
      "xc": null,
      "xd": null,
      "tradingCommencement": null,
      "tradingSuspended": null,
      "paymentDate": null,
      "agmDate": null,
      "dateOfAgmInitial": null,
      "logoUrl": null,
      "remarks": null
    },
    {
      "id": 26861,
      "createdDate": 1751631360000,
      "dateOfAnnouncement": "04 Jul 2025",
      "announcementId": 31959,
      "announcementCategory": "ANNUAL GENERAL MEETING - APPROVED",
      "company": "AITKEN SPENCE HOTEL HOLDINGS PLC",
      "type": "new",
      "symbol": null,
      "recordDate": null,
      "allotment": null,
      "xr": null,
      "xc": null,
      "xd": null,
      "tradingCommencement": null,
      "tradingSuspended": null,
      "paymentDate": null,
      "agmDate": null,
      "dateOfAgmInitial": null,
      "logoUrl": null,
      "remarks": null
    },
    {
      "id": 26550,
      "createdDate": 1750160851000,
      "dateOfAnnouncement": "17 Jun 2025",
      "announcementId": 31568,
      "announcementCategory": "CIRCULAR TO SHAREHOLDERS",
      "company": "AITKEN SPENCE HOTEL HOLDINGS PLC",
      "type": "new",
      "symbol": null,
      "recordDate": null,
      "allotment": null,
      "xr": null,
      "xc": null,
      "xd": null,
      "tradingCommencement": null,
      "tradingSuspended": null,
      "paymentDate": null,
      "agmDate": null,
      "dateOfAgmInitial": null,
      "logoUrl": null,
      "remarks": null
    },
    {
      "id": 26547,
      "createdDate": 1750160611000,
      "dateOfAnnouncement": "17 Jun 2025",
      "announcementId": 31567,
      "announcementCategory": "ANNUAL GENERAL MEETING - INITIAL",
      "company": "AITKEN SPENCE HOTEL HOLDINGS PLC",
      "type": "new",
      "symbol": null,
      "recordDate": null,
      "allotment": null,
      "xr": null,
      "xc": null,
      "xd": null,
      "tradingCommencement": null,
      "tradingSuspended": null,
      "paymentDate": null,
      "agmDate": null,
      "dateOfAgmInitial": null,
      "logoUrl": null,
      "remarks": null
    },
    {
      "id": 25671,
      "createdDate": 1743764177000,
      "dateOfAnnouncement": "04 Apr 2025",
      "announcementId": 30445,
      "announcementCategory": "APPOINTMENT OF DIRECTORS",
      "company": "AITKEN SPENCE HOTEL HOLDINGS PLC",
      "type": "new",
      "symbol": null,
      "recordDate": null,
      "allotment": null,
      "xr": null,
      "xc": null,
      "xd": null,
      "tradingCommencement": null,
      "tradingSuspended": null,
      "paymentDate": null,
      "agmDate": null,
      "dateOfAgmInitial": null,
      "logoUrl": null,
      "remarks": null
    },
    {
      "id": 25619,
      "createdDate": 1743586826000,
      "dateOfAnnouncement": "01 Apr 2025",
      "announcementId": 30345,
      "announcementCategory": "CORPORATE DISCLOSURE",
      "company": "AITKEN SPENCE HOTEL HOLDINGS PLC",
      "type": "new",
      "symbol": null,
      "recordDate": null,
      "allotment": null,
      "xr": null,
      "xc": null,
      "xd": null,
      "tradingCommencement": null,
      "tradingSuspended": null,
      "paymentDate": null,
      "agmDate": null,
      "dateOfAgmInitial": null,
      "logoUrl": null,
      "remarks": null
    },
    {
      "id": 25598,
      "createdDate": 1743525203000,
      "dateOfAnnouncement": "01 Apr 2025",
      "announcementId": 30344,
      "announcementCategory": "APPOINTMENT OF DIRECTORS",
      "company": "AITKEN SPENCE HOTEL HOLDINGS PLC",
      "type": "new",
      "symbol": null,
      "recordDate": null,
      "allotment": null,
      "xr": null,
      "xc": null,
      "xd": null,
      "tradingCommencement": null,
      "tradingSuspended": null,
      "paymentDate": null,
      "agmDate": null,
      "dateOfAgmInitial": null,
      "logoUrl": null,
      "remarks": null
    },
    {
      "id": 25266,
      "createdDate": 1741255946000,
      "dateOfAnnouncement": "06 Mar 2025",
      "announcementId": 29944,
      "announcementCategory": "NON-COMPLIANCE OF CORPORATE GOVERNANCE RULES",
      "company": "AITKEN SPENCE HOTEL HOLDINGS PLC",
      "type": "new",
      "symbol": null,
      "recordDate": null,
      "allotment": null,
      "xr": null,
      "xc": null,
      "xd": null,
      "tradingCommencement": null,
      "tradingSuspended": null,
      "paymentDate": null,
      "agmDate": null,
      "dateOfAgmInitial": null,
      "logoUrl": null,
      "remarks": null
    },
    {
      "id": 24954,
      "createdDate": 1738899680000,
      "dateOfAnnouncement": "07 Feb 2025",
      "announcementId": 29523,
      "announcementCategory": "CORPORATE DISCLOSURE",
      "company": "AITKEN SPENCE HOTEL HOLDINGS PLC",
      "type": "new",
      "symbol": null,
      "recordDate": null,
      "allotment": null,
      "xr": null,
      "xc": null,
      "xd": null,
      "tradingCommencement": null,
      "tradingSuspended": null,
      "paymentDate": null,
      "agmDate": null,
      "dateOfAgmInitial": null,
      "logoUrl": null,
      "remarks": null
    },
    {
      "id": 24952,
      "createdDate": 1738899341000,
      "dateOfAnnouncement": "06 Feb 2025",
      "announcementId": 29510,
      "announcementCategory": "APPOINTMENT OF CHAIRPERSON",
      "company": "AITKEN SPENCE HOTEL HOLDINGS PLC",
      "type": "new",
      "symbol": null,
      "recordDate": null,
      "allotment": null,
      "xr": null,
      "xc": null,
      "xd": null,
      "tradingCommencement": null,
      "tradingSuspended": null,
      "paymentDate": null,
      "agmDate": null,
      "dateOfAgmInitial": null,
      "logoUrl": null,
      "remarks": null
    },
    {
      "id": 24936,
      "createdDate": 1738820909000,
      "dateOfAnnouncement": "06 Feb 2025",
      "announcementId": 29485,
      "announcementCategory": "NON-COMPLIANCE OF CORPORATE GOVERNANCE RULES",
      "company": "AITKEN SPENCE HOTEL HOLDINGS PLC",
      "type": "new",
      "symbol": null,
      "recordDate": null,
      "allotment": null,
      "xr": null,
      "xc": null,
      "xd": null,
      "tradingCommencement": null,
      "tradingSuspended": null,
      "paymentDate": null,
      "agmDate": null,
      "dateOfAgmInitial": null,
      "logoUrl": null,
      "remarks": null
    },
    {
      "id": 24902,
      "createdDate": 1738582790000,
      "dateOfAnnouncement": "03 Feb 2025",
      "announcementId": 29446,
      "announcementCategory": "DEMISE OF A DIRECTOR",
      "company": "AITKEN SPENCE HOTEL HOLDINGS PLC",
      "type": "new",
      "symbol": null,
      "recordDate": null,
      "allotment": null,
      "xr": null,
      "xc": null,
      "xd": null,
      "tradingCommencement": null,
      "tradingSuspended": null,
      "paymentDate": null,
      "agmDate": null,
      "dateOfAgmInitial": null,
      "logoUrl": null,
      "remarks": null
    },
    {
      "id": 24721,
      "createdDate": 1737624290000,
      "dateOfAnnouncement": "23 Jan 2025",
      "announcementId": 29210,
      "announcementCategory": "DEALINGS BY DIRECTORS",
      "company": "AITKEN SPENCE HOTEL HOLDINGS PLC",
      "type": "new",
      "symbol": null,
      "recordDate": null,
      "allotment": null,
      "xr": null,
      "xc": null,
      "xd": null,
      "tradingCommencement": null,
      "tradingSuspended": null,
      "paymentDate": null,
      "agmDate": null,
      "dateOfAgmInitial": null,
      "logoUrl": null,
      "remarks": null
    },
    {
      "id": 24613,
      "createdDate": 1736421966000,
      "dateOfAnnouncement": "09 Jan 2025",
      "announcementId": 29047,
      "announcementCategory": "RESIGNATION OF DIRECTORS",
      "company": "AITKEN SPENCE HOTEL HOLDINGS PLC",
      "type": "new",
      "symbol": null,
      "recordDate": null,
      "allotment": null,
      "xr": null,
      "xc": null,
      "xd": null,
      "tradingCommencement": null,
      "tradingSuspended": null,
      "paymentDate": null,
      "agmDate": null,
      "dateOfAgmInitial": null,
      "logoUrl": null,
      "remarks": null
    },
    {
      "id": 24320,
      "createdDate": 1735658943000,
      "dateOfAnnouncement": "31 Dec 2024",
      "announcementId": 28642,
      "announcementCategory": "CORPORATE DISCLOSURE",
      "company": "AITKEN SPENCE HOTEL HOLDINGS PLC",
      "type": "new",
      "symbol": null,
      "recordDate": null,
      "allotment": null,
      "xr": null,
      "xc": null,
      "xd": null,
      "tradingCommencement": null,
      "tradingSuspended": null,
      "paymentDate": null,
      "agmDate": null,
      "dateOfAgmInitial": null,
      "logoUrl": null,
      "remarks": null
    },
    {
      "id": 24319,
      "createdDate": 1735658817000,
      "dateOfAnnouncement": "31 Dec 2024",
      "announcementId": 28643,
      "announcementCategory": "CORPORATE DISCLOSURE",
      "company": "AITKEN SPENCE HOTEL HOLDINGS PLC",
      "type": "new",
      "symbol": null,
      "recordDate": null,
      "allotment": null,
      "xr": null,
      "xc": null,
      "xd": null,
      "tradingCommencement": null,
      "tradingSuspended": null,
      "paymentDate": null,
      "agmDate": null,
      "dateOfAgmInitial": null,
      "logoUrl": null,
      "remarks": null
    },
    {
      "id": 24295,
      "createdDate": 1735645232000,
      "dateOfAnnouncement": "31 Dec 2024",
      "announcementId": 28641,
      "announcementCategory": "APPOINTMENT OF DIRECTORS",
      "company": "AITKEN SPENCE HOTEL HOLDINGS PLC",
      "type": "new",
      "symbol": null,
      "recordDate": null,
      "allotment": null,
      "xr": null,
      "xc": null,
      "xd": null,
      "tradingCommencement": null,
      "tradingSuspended": null,
      "paymentDate": null,
      "agmDate": null,
      "dateOfAgmInitial": null,
      "logoUrl": null,
      "remarks": null
    },
    {
      "id": 23832,
      "createdDate": 1733136782000,
      "dateOfAnnouncement": "02 Dec 2024",
      "announcementId": 28097,
      "announcementCategory": "APPOINTMENT OF DIRECTORS",
      "company": "AITKEN SPENCE HOTEL HOLDINGS PLC",
      "type": "new",
      "symbol": null,
      "recordDate": null,
      "allotment": null,
      "xr": null,
      "xc": null,
      "xd": null,
      "tradingCommencement": null,
      "tradingSuspended": null,
      "paymentDate": null,
      "agmDate": null,
      "dateOfAgmInitial": null,
      "logoUrl": null,
      "remarks": null
    },
    {
      "id": 23720,
      "createdDate": 1732533422000,
      "dateOfAnnouncement": "25 Nov 2024",
      "announcementId": 27961,
      "announcementCategory": "RESIGNATION OF DIRECTORS",
      "company": "AITKEN SPENCE HOTEL HOLDINGS PLC",
      "type": "new",
      "symbol": null,
      "recordDate": null,
      "allotment": null,
      "xr": null,
      "xc": null,
      "xd": null,
      "tradingCommencement": null,
      "tradingSuspended": null,
      "paymentDate": null,
      "agmDate": null,
      "dateOfAgmInitial": null,
      "logoUrl": null,
      "remarks": null
    },
    {
      "id": 23580,
      "createdDate": 1731409526000,
      "dateOfAnnouncement": "12 Nov 2024",
      "announcementId": 27786,
      "announcementCategory": "CORPORATE DISCLOSURE",
      "company": "AITKEN SPENCE HOTEL HOLDINGS PLC",
      "type": "new",
      "symbol": null,
      "recordDate": null,
      "allotment": null,
      "xr": null,
      "xc": null,
      "xd": null,
      "tradingCommencement": null,
      "tradingSuspended": null,
      "paymentDate": null,
      "agmDate": null,
      "dateOfAgmInitial": null,
      "logoUrl": null,
      "remarks": null
    },
    {
      "id": 22941,
      "createdDate": 1727698402000,
      "dateOfAnnouncement": "30 Sep 2024",
      "announcementId": 26985,
      "announcementCategory": "CORPORATE DISCLOSURE",
      "company": "AITKEN SPENCE HOTEL HOLDINGS PLC",
      "type": "new",
      "symbol": null,
      "recordDate": null,
      "allotment": null,
      "xr": null,
      "xc": null,
      "xd": null,
      "tradingCommencement": null,
      "tradingSuspended": null,
      "paymentDate": null,
      "agmDate": null,
      "dateOfAgmInitial": null,
      "logoUrl": null,
      "remarks": null
    },
    {
      "id": 21962,
      "createdDate": 1722943461000,
      "dateOfAnnouncement": "06 Aug 2024",
      "announcementId": 25782,
      "announcementCategory": "ANNUAL GENERAL MEETING - APPROVED",
      "company": "AITKEN SPENCE HOTEL HOLDINGS PLC",
      "type": "new",
      "symbol": null,
      "recordDate": null,
      "allotment": null,
      "xr": null,
      "xc": null,
      "xd": null,
      "tradingCommencement": null,
      "tradingSuspended": null,
      "paymentDate": null,
      "agmDate": null,
      "dateOfAgmInitial": null,
      "logoUrl": null,
      "remarks": null
    },
    {
      "id": 21689,
      "createdDate": 1721041721000,
      "dateOfAnnouncement": "15 Jul 2024",
      "announcementId": 25439,
      "announcementCategory": "CIRCULAR TO SHAREHOLDERS",
      "company": "AITKEN SPENCE HOTEL HOLDINGS PLC",
      "type": "new",
      "symbol": null,
      "recordDate": null,
      "allotment": null,
      "xr": null,
      "xc": null,
      "xd": null,
      "tradingCommencement": null,
      "tradingSuspended": null,
      "paymentDate": null,
      "agmDate": null,
      "dateOfAgmInitial": null,
      "logoUrl": null,
      "remarks": null
    },
    {
      "id": 21686,
      "createdDate": 1721041459000,
      "dateOfAnnouncement": "15 Jul 2024",
      "announcementId": 25437,
      "announcementCategory": "ANNUAL GENERAL MEETING - INITIAL",
      "company": "AITKEN SPENCE HOTEL HOLDINGS PLC",
      "type": "new",
      "symbol": null,
      "recordDate": null,
      "allotment": null,
      "xr": null,
      "xc": null,
      "xd": null,
      "tradingCommencement": null,
      "tradingSuspended": null,
      "paymentDate": null,
      "agmDate": null,
      "dateOfAgmInitial": null,
      "logoUrl": null,
      "remarks": null
    },
    {
      "id": 20331,
      "createdDate": 1712659519000,
      "dateOfAnnouncement": "09 Apr 2024",
      "announcementId": 23826,
      "announcementCategory": "CHANGE OF COMPANY SECRETARY/REGISTRAR",
      "company": "AITKEN SPENCE HOTEL HOLDINGS PLC",
      "type": "new",
      "symbol": null,
      "recordDate": null,
      "allotment": null,
      "xr": null,
      "xc": null,
      "xd": null,
      "tradingCommencement": null,
      "tradingSuspended": null,
      "paymentDate": null,
      "agmDate": null,
      "dateOfAgmInitial": null,
      "logoUrl": null,
      "remarks": null
    },
    {
      "id": 19497,
      "createdDate": 1705035064000,
      "dateOfAnnouncement": "11 Jan 2024",
      "announcementId": 22759,
      "announcementCategory": "APPOINTMENT OF DIRECTORS",
      "company": "AITKEN SPENCE HOTEL HOLDINGS PLC",
      "type": "new",
      "symbol": null,
      "recordDate": null,
      "allotment": null,
      "xr": null,
      "xc": null,
      "xd": null,
      "tradingCommencement": null,
      "tradingSuspended": null,
      "paymentDate": null,
      "agmDate": null,
      "dateOfAgmInitial": null,
      "logoUrl": null,
      "remarks": null
    },
    {
      "id": 18943,
      "createdDate": 1700476174000,
      "dateOfAnnouncement": "20 Nov 2023",
      "announcementId": 22082,
      "announcementCategory": "DEMISE OF A DIRECTOR",
      "company": "AITKEN SPENCE HOTEL HOLDINGS PLC",
      "type": "new",
      "symbol": null,
      "recordDate": null,
      "allotment": null,
      "xr": null,
      "xc": null,
      "xd": null,
      "tradingCommencement": null,
      "tradingSuspended": null,
      "paymentDate": null,
      "agmDate": null,
      "dateOfAgmInitial": null,
      "logoUrl": null,
      "remarks": null
    },
    {
      "id": 18764,
      "createdDate": 1698746517000,
      "dateOfAnnouncement": "31 Oct 2023",
      "announcementId": 21822,
      "announcementCategory": "CORPORATE DISCLOSURE",
      "company": "AITKEN SPENCE HOTEL HOLDINGS PLC",
      "type": "new",
      "symbol": null,
      "recordDate": null,
      "allotment": null,
      "xr": null,
      "xc": null,
      "xd": null,
      "tradingCommencement": null,
      "tradingSuspended": null,
      "paymentDate": null,
      "agmDate": null,
      "dateOfAgmInitial": null,
      "logoUrl": null,
      "remarks": null
    },
    {
      "id": 18388,
      "createdDate": 1695278915000,
      "dateOfAnnouncement": "21 Sep 2023",
      "announcementId": 21326,
      "announcementCategory": "DEALINGS BY DIRECTORS",
      "company": "AITKEN SPENCE HOTEL HOLDINGS PLC",
      "type": "new",
      "symbol": null,
      "recordDate": null,
      "allotment": null,
      "xr": null,
      "xc": null,
      "xd": null,
      "tradingCommencement": null,
      "tradingSuspended": null,
      "paymentDate": null,
      "agmDate": null,
      "dateOfAgmInitial": null,
      "logoUrl": null,
      "remarks": null
    },
    {
      "id": 18336,
      "createdDate": 1694770965000,
      "dateOfAnnouncement": "15 Sep 2023",
      "announcementId": 21268,
      "announcementCategory": "CORPORATE DISCLOSURE",
      "company": "AITKEN SPENCE HOTEL HOLDINGS PLC",
      "type": "new",
      "symbol": null,
      "recordDate": null,
      "allotment": null,
      "xr": null,
      "xc": null,
      "xd": null,
      "tradingCommencement": null,
      "tradingSuspended": null,
      "paymentDate": null,
      "agmDate": null,
      "dateOfAgmInitial": null,
      "logoUrl": null,
      "remarks": null
    },
    {
      "id": 18327,
      "createdDate": 1694684673000,
      "dateOfAnnouncement": "14 Sep 2023",
      "announcementId": 21252,
      "announcementCategory": "DEALINGS BY DIRECTORS",
      "company": "AITKEN SPENCE HOTEL HOLDINGS PLC",
      "type": "new",
      "symbol": null,
      "recordDate": null,
      "allotment": null,
      "xr": null,
      "xc": null,
      "xd": null,
      "tradingCommencement": null,
      "tradingSuspended": null,
      "paymentDate": null,
      "agmDate": null,
      "dateOfAgmInitial": null,
      "logoUrl": null,
      "remarks": null
    },
    {
      "id": 18292,
      "createdDate": 1694426868000,
      "dateOfAnnouncement": "11 Sep 2023",
      "announcementId": 21209,
      "announcementCategory": "CORPORATE DISCLOSURE",
      "company": "AITKEN SPENCE HOTEL HOLDINGS PLC",
      "type": "new",
      "symbol": null,
      "recordDate": null,
      "allotment": null,
      "xr": null,
      "xc": null,
      "xd": null,
      "tradingCommencement": null,
      "tradingSuspended": null,
      "paymentDate": null,
      "agmDate": null,
      "dateOfAgmInitial": null,
      "logoUrl": null,
      "remarks": null
    },
    {
      "id": 18016,
      "createdDate": 1693307385000,
      "dateOfAnnouncement": "29 Aug 2023",
      "announcementId": 20888,
      "announcementCategory": "DEALINGS BY DIRECTORS",
      "company": "AITKEN SPENCE HOTEL HOLDINGS PLC",
      "type": "new",
      "symbol": null,
      "recordDate": null,
      "allotment": null,
      "xr": null,
      "xc": null,
      "xd": null,
      "tradingCommencement": null,
      "tradingSuspended": null,
      "paymentDate": null,
      "agmDate": null,
      "dateOfAgmInitial": null,
      "logoUrl": null,
      "remarks": null
    },
    {
      "id": 17405,
      "createdDate": 1688197828000,
      "dateOfAnnouncement": "30 Jun 2023",
      "announcementId": 20143,
      "announcementCategory": "ANNUAL GENERAL MEETING - APPROVED",
      "company": "AITKEN SPENCE HOTEL HOLDINGS PLC",
      "type": "new",
      "symbol": null,
      "recordDate": null,
      "allotment": null,
      "xr": null,
      "xc": null,
      "xd": null,
      "tradingCommencement": null,
      "tradingSuspended": null,
      "paymentDate": null,
      "agmDate": null,
      "dateOfAgmInitial": null,
      "logoUrl": null,
      "remarks": null
    },
    {
      "id": 17104,
      "createdDate": 1686133954000,
      "dateOfAnnouncement": "07 Jun 2023",
      "announcementId": 19770,
      "announcementCategory": "ANNUAL GENERAL MEETING - INITIAL",
      "company": "AITKEN SPENCE HOTEL HOLDINGS PLC",
      "type": "new",
      "symbol": null,
      "recordDate": null,
      "allotment": null,
      "xr": null,
      "xc": null,
      "xd": null,
      "tradingCommencement": null,
      "tradingSuspended": null,
      "paymentDate": null,
      "agmDate": null,
      "dateOfAgmInitial": null,
      "logoUrl": null,
      "remarks": null
    },
    {
      "id": 17101,
      "createdDate": 1686133825000,
      "dateOfAnnouncement": "07 Jun 2023",
      "announcementId": 19771,
      "announcementCategory": "CIRCULAR TO SHAREHOLDERS",
      "company": "AITKEN SPENCE HOTEL HOLDINGS PLC",
      "type": "new",
      "symbol": null,
      "recordDate": null,
      "allotment": null,
      "xr": null,
      "xc": null,
      "xd": null,
      "tradingCommencement": null,
      "tradingSuspended": null,
      "paymentDate": null,
      "agmDate": null,
      "dateOfAgmInitial": null,
      "logoUrl": null,
      "remarks": null
    },
    {
      "id": 16671,
      "createdDate": 1682569921000,
      "dateOfAnnouncement": "27 Apr 2023",
      "announcementId": 19247,
      "announcementCategory": "APPOINTMENT OF DIRECTORS",
      "company": "AITKEN SPENCE HOTEL HOLDINGS PLC",
      "type": "new",
      "symbol": null,
      "recordDate": null,
      "allotment": null,
      "xr": null,
      "xc": null,
      "xd": null,
      "tradingCommencement": null,
      "tradingSuspended": null,
      "paymentDate": null,
      "agmDate": null,
      "dateOfAgmInitial": null,
      "logoUrl": null,
      "remarks": null
    },
    {
      "id": 16133,
      "createdDate": 1677496718000,
      "dateOfAnnouncement": "27 Feb 2023",
      "announcementId": 18632,
      "announcementCategory": "CORPORATE DISCLOSURE",
      "company": "AITKEN SPENCE HOTEL HOLDINGS PLC",
      "type": "new",
      "symbol": null,
      "recordDate": null,
      "allotment": null,
      "xr": null,
      "xc": null,
      "xd": null,
      "tradingCommencement": null,
      "tradingSuspended": null,
      "paymentDate": null,
      "agmDate": null,
      "dateOfAgmInitial": null,
      "logoUrl": null,
      "remarks": null
    },
    {
      "id": 13564,
      "createdDate": 1656586189000,
      "dateOfAnnouncement": "30 Jun 2022",
      "announcementId": 15651,
      "announcementCategory": "ANNUAL GENERAL MEETING - APPROVED",
      "company": "AITKEN SPENCE HOTEL HOLDINGS PLC",
      "type": "new",
      "symbol": null,
      "recordDate": null,
      "allotment": null,
      "xr": null,
      "xc": null,
      "xd": null,
      "tradingCommencement": null,
      "tradingSuspended": null,
      "paymentDate": null,
      "agmDate": null,
      "dateOfAgmInitial": null,
      "logoUrl": null,
      "remarks": null
    },
    {
      "id": 13205,
      "createdDate": 1654596268000,
      "dateOfAnnouncement": "07 Jun 2022",
      "announcementId": 15221,
      "announcementCategory": "CIRCULAR TO SHAREHOLDERS",
      "company": "AITKEN SPENCE HOTEL HOLDINGS PLC",
      "type": "new",
      "symbol": null,
      "recordDate": null,
      "allotment": null,
      "xr": null,
      "xc": null,
      "xd": null,
      "tradingCommencement": null,
      "tradingSuspended": null,
      "paymentDate": null,
      "agmDate": null,
      "dateOfAgmInitial": null,
      "logoUrl": null,
      "remarks": null
    },
    {
      "id": 13203,
      "createdDate": 1654596144000,
      "dateOfAnnouncement": "07 Jun 2022",
      "announcementId": 15220,
      "announcementCategory": "ANNUAL GENERAL MEETING - INITIAL",
      "company": "AITKEN SPENCE HOTEL HOLDINGS PLC",
      "type": "new",
      "symbol": null,
      "recordDate": null,
      "allotment": null,
      "xr": null,
      "xc": null,
      "xd": null,
      "tradingCommencement": null,
      "tradingSuspended": null,
      "paymentDate": null,
      "agmDate": null,
      "dateOfAgmInitial": null,
      "logoUrl": null,
      "remarks": null
    },
    {
      "id": 8927,
      "createdDate": 1625046255000,
      "dateOfAnnouncement": "30 Jun 2021",
      "announcementId": 10342,
      "announcementCategory": "ANNUAL GENERAL MEETING - APPROVED",
      "company": "AITKEN SPENCE HOTEL HOLDINGS PLC",
      "type": "new",
      "symbol": null,
      "recordDate": null,
      "allotment": null,
      "xr": null,
      "xc": null,
      "xd": null,
      "tradingCommencement": null,
      "tradingSuspended": null,
      "paymentDate": null,
      "agmDate": null,
      "dateOfAgmInitial": null,
      "logoUrl": null,
      "remarks": null
    },
    {
      "id": 8612,
      "createdDate": 1623061294000,
      "dateOfAnnouncement": "07 Jun 2021",
      "announcementId": 9978,
      "announcementCategory": "CIRCULAR TO SHAREHOLDERS",
      "company": "AITKEN SPENCE HOTEL HOLDINGS PLC",
      "type": "new",
      "symbol": null,
      "recordDate": null,
      "allotment": null,
      "xr": null,
      "xc": null,
      "xd": null,
      "tradingCommencement": null,
      "tradingSuspended": null,
      "paymentDate": null,
      "agmDate": null,
      "dateOfAgmInitial": null,
      "logoUrl": null,
      "remarks": null
    },
    {
      "id": 8608,
      "createdDate": 1623060321000,
      "dateOfAnnouncement": "07 Jun 2021",
      "announcementId": 9973,
      "announcementCategory": "ANNUAL GENERAL MEETING - INITIAL",
      "company": "AITKEN SPENCE HOTEL HOLDINGS PLC",
      "type": "new",
      "symbol": null,
      "recordDate": null,
      "allotment": null,
      "xr": null,
      "xc": null,
      "xd": null,
      "tradingCommencement": null,
      "tradingSuspended": null,
      "paymentDate": null,
      "agmDate": null,
      "dateOfAgmInitial": null,
      "logoUrl": null,
      "remarks": null
    },
    {
      "id": 6748,
      "createdDate": 1608632166000,
      "dateOfAnnouncement": "22 Dec 2020",
      "announcementId": 7800,
      "announcementCategory": "DEALINGS BY DIRECTORS",
      "company": "AITKEN SPENCE HOTEL HOLDINGS PLC",
      "type": "new",
      "symbol": null,
      "recordDate": null,
      "allotment": null,
      "xr": null,
      "xc": null,
      "xd": null,
      "tradingCommencement": null,
      "tradingSuspended": null,
      "paymentDate": null,
      "agmDate": null,
      "dateOfAgmInitial": null,
      "logoUrl": null,
      "remarks": null
    },
    {
      "id": 4644,
      "createdDate": 1593510248000,
      "dateOfAnnouncement": "30 Jun 2020",
      "announcementId": 5260,
      "announcementCategory": "ANNUAL GENERAL MEETING - APPROVED",
      "company": "AITKEN SPENCE HOTEL HOLDINGS PLC",
      "type": "new",
      "symbol": null,
      "recordDate": null,
      "allotment": null,
      "xr": null,
      "xc": null,
      "xd": null,
      "tradingCommencement": null,
      "tradingSuspended": null,
      "paymentDate": null,
      "agmDate": null,
      "dateOfAgmInitial": null,
      "logoUrl": null,
      "remarks": null
    },
    {
      "id": 4398,
      "createdDate": 1591609699000,
      "dateOfAnnouncement": "08 Jun 2020",
      "announcementId": 4939,
      "announcementCategory": "ANNUAL GENERAL MEETING - INITIAL",
      "company": "AITKEN SPENCE HOTEL HOLDINGS PLC",
      "type": "new",
      "symbol": null,
      "recordDate": null,
      "allotment": null,
      "xr": null,
      "xc": null,
      "xd": null,
      "tradingCommencement": null,
      "tradingSuspended": null,
      "paymentDate": null,
      "agmDate": null,
      "dateOfAgmInitial": null,
      "logoUrl": null,
      "remarks": null
    },
    {
      "id": 3874,
      "createdDate": 1589167327000,
      "dateOfAnnouncement": "10 May 2020",
      "announcementId": 4356,
      "announcementCategory": "DISCLOSURE REGARDING IMPACT OF COVID-19 ON LISTED COMPANIES",
      "company": "AITKEN SPENCE HOTEL HOLDINGS PLC",
      "type": "new",
      "symbol": null,
      "recordDate": null,
      "allotment": null,
      "xr": null,
      "xc": null,
      "xd": null,
      "tradingCommencement": null,
      "tradingSuspended": null,
      "paymentDate": null,
      "agmDate": null,
      "dateOfAgmInitial": null,
      "logoUrl": null,
      "remarks": null
    }
  ]
}